Metadata-Version: 2.2
Name: read_acq
Version: 1.1.1
Summary: Read/Write ACQ Spectrum Files
Author-email: Steven Murray <steven.murray@sns.it>
License: MIT
Project-URL: Documentation, https://read-acq.readthedocs.io/en/latest/
Project-URL: Repository, https://github.com/edges-collab/edges-cal
Project-URL: Issues, https://github.com/edges-collab/edges-cal/issues
Project-URL: Changelog, https://github.com/edges-collab/edges-cal/releases
Classifier: Development Status :: 5 - Production/Stable
Classifier: Intended Audience :: Science/Research
Classifier: License :: OSI Approved :: MIT License
Classifier: Operating System :: POSIX
Classifier: Operating System :: Unix
Classifier: Programming Language :: Python
Classifier: Programming Language :: Python :: 3
Classifier: Programming Language :: Python :: 3 :: Only
Classifier: Programming Language :: Python :: Implementation :: CPython
Requires-Python: >=3.9
License-File: LICENSE.txt
Requires-Dist: click
Requires-Dist: numpy
Requires-Dist: pygsdata
Requires-Dist: scipy
Requires-Dist: tqdm
Provides-Extra: dev
Requires-Dist: pre-commit; extra == "dev"
Requires-Dist: pytest; extra == "dev"
Requires-Dist: pytest-cov; extra == "dev"
